tga_data_analysis/__init__.py
tga_data_analysis/kas_kinetics.py
tga_data_analysis/measure.py
tga_data_analysis/tga.py
tga_data_analysis-2.2.0.dist-info/METADATA
tga_data_analysis-2.2.0.dist-info/WHEEL
tga_data_analysis-2.2.0.dist-info/top_level.txt
tga_data_analysis-2.2.0.dist-info/RECORD
